Metadata-Version: 2.4
Name: iis-vpro
Version: 1.1
Summary: Example Python Module
Author-email: IT Services <pypi@iis.fraunhofer.de>
Project-URL: Homepage, https://www.iis.fraunhofer.de/
Project-URL: Bug Tracker, https://www.iis.fraunhofer.de/
Classifier: Programming Language :: Python :: 3
Classifier: License :: OSI Approved :: MIT License
Classifier: Operating System :: OS Independent
Requires-Python: >=3.10
